bauwerk/__init__.py
bauwerk/benchmarks.py
bauwerk/constants.py
bauwerk/eval.py
bauwerk/data/__init__.py
bauwerk/data/default_load_data.txt
bauwerk/data/default_solar_data.txt
bauwerk/data/assets/__init__.py
bauwerk/data/assets/bauwerk_game_logo.png
bauwerk/data/assets/house.png
bauwerk/data/assets/house_v2.png
bauwerk/envs/__init__.py
bauwerk/envs/distributions.py
bauwerk/envs/registration.py
bauwerk/envs/solar_battery_house.py
bauwerk/envs/solvers.py
bauwerk/envs/wrappers.py
bauwerk/envs/components/__init__.py
bauwerk/envs/components/base.py
bauwerk/envs/components/battery.py
bauwerk/envs/components/grid.py
bauwerk/envs/components/load.py
bauwerk/envs/components/solar.py
bauwerk/exp/__init__.py
bauwerk/exp/core.py
bauwerk/utils/__init__.py
bauwerk/utils/compat.py
bauwerk/utils/data.py
bauwerk/utils/gym.py
bauwerk/utils/logging.py
bauwerk/utils/notation.py
bauwerk/utils/plotting.py
bauwerk/utils/sb3.py
bauwerk/utils/testing.py
bauwerk/widget/__init__.py
bauwerk/widget/core.py
bauwerk-0.3.2.dist-info/AUTHORS.rst
bauwerk-0.3.2.dist-info/LICENSE
bauwerk-0.3.2.dist-info/METADATA
bauwerk-0.3.2.dist-info/WHEEL
bauwerk-0.3.2.dist-info/entry_points.txt
bauwerk-0.3.2.dist-info/top_level.txt
bauwerk-0.3.2.dist-info/RECORD
