Metadata-Version: 2.1
Name: bauwerk
Version: 0.3.2
Summary: Simple building control environments for reinforcement learning.
Home-page: https://github.com/rdnfn/bauwerk
Author: rdnfn
License: MIT license
Keywords: bauwerk
Classifier: Development Status :: 2 - Pre-Alpha
Classifier: Intended Audience :: Developers
Classifier: License :: OSI Approved :: MIT License
Classifier: Natural Language :: English
Classifier: Programming Language :: Python :: 3
Classifier: Programming Language :: Python :: 3.7
Classifier: Programming Language :: Python :: 3.8
Classifier: Programming Language :: Python :: 3.9
Classifier: Programming Language :: Python :: 3.10
Requires-Python: >=3.6
License-File: LICENSE
License-File: AUTHORS.rst
Requires-Dist: gym
Requires-Dist: numpy (>=1.20)
Requires-Dist: loguru
Requires-Dist: importlib-resources ; python_version < "3.9"
Provides-Extra: exp
Requires-Dist: hydra-core ; extra == 'exp'
Requires-Dist: stable-baselines3 ; extra == 'exp'
Requires-Dist: wandb ; extra == 'exp'
Provides-Extra: opt
Requires-Dist: cvxpy ; extra == 'opt'
Provides-Extra: widget
Requires-Dist: ipympl ; extra == 'widget'
